gdm_robotics/__init__.py
gdm_robotics/adapters/dm_env_to_gdmr_env_wrapper.py
gdm_robotics/adapters/gymnasium_env_to_gdmr_env_wrapper.py
gdm_robotics/interfaces/environment.py
gdm_robotics/interfaces/episodic_logger.py
gdm_robotics/interfaces/policy.py
gdm_robotics/interfaces/types.py
gdm_robotics/runtime/runloop.py
gdm_robotics/runtime/scope.py
gdm_robotics/testing/specs_utils.py
gdm_robotics-1.0.1.dist-info/licenses/LICENSE
gdm_robotics-1.0.1.dist-info/WHEEL
gdm_robotics-1.0.1.dist-info/METADATA
gdm_robotics-1.0.1.dist-info/RECORD
