Metadata-Version: 2.4
Name: gdm_robotics
Version: 1.0.1
Summary: Google DeepMind Robotics Interfaces and utilities.
Keywords: RL,Reinforcement Learning,AI,ML
Author-email: Google DeepMind <robotics+oss@google.com>
Maintainer-email: Claudio Fantacci <cfantacci@google.com>, Francesco Romano <fraromano@google.com>
Requires-Python: >=3.10
License-Expression: Apache-2.0
Classifier: Development Status :: 5 - Production/Stable
Classifier: Intended Audience :: Science/Research
Classifier: Topic :: Scientific/Engineering :: Artificial Intelligence
Classifier: Typing :: Typed
License-File: LICENSE
Requires-Dist: numpy >= 2.0, < 3.0
Requires-Dist: absl-py
Requires-Dist: dm-env
Requires-Dist: typing-extensions
Requires-Dist: pytest
Requires-Dist: gymnasium >= 1.0.0
Project-URL: Issues, https://github.com/google-deepmind/gdm_robotics/issues
Project-URL: Repository, https://github.com/google-deepmind/gdm_robotics.git
